parql/__init__.py
parql/cli.py
parql/commands/__init__.py
parql/commands/advanced.py
parql/commands/system.py
parql/commands/utilities.py
parql/core/__init__.py
parql/core/context.py
parql/core/engine.py
parql/utils/__init__.py
parql/utils/exceptions.py
parql/utils/output.py
parql/utils/schema.py
parql/utils/storage.py
parql-1.0.4.dist-info/licenses/LICENSE
parql-1.0.4.dist-info/METADATA
parql-1.0.4.dist-info/WHEEL
parql-1.0.4.dist-info/entry_points.txt
parql-1.0.4.dist-info/top_level.txt
parql-1.0.4.dist-info/RECORD
