Metadata-Version: 2.4
Name: parql
Version: 1.0.4
Summary: A command-line tool for querying and manipulating Parquet datasets
Author-email: Abdul Rafey <abdulrafey38@gmail.com>
Maintainer-email: Abdul Rafey <abdulrafey38@gmail.com>
License: MIT
Project-URL: Homepage, https://github.com/abdulrafey38/parql
Project-URL: Documentation, https://github.com/abdulrafey38/parql
Project-URL: Repository, https://github.com/abdulrafey38/parql
Project-URL: Issues, https://github.com/abdulrafey38/parql/issues
Keywords: parquet,sql,data,cli,duckdb,pandas
Classifier: Development Status :: 5 - Production/Stable
Classifier: Intended Audience :: Developers
Classifier: Operating System :: OS Independent
Classifier: Programming Language :: Python :: 3
Classifier: Programming Language :: Python :: 3.9
Classifier: Programming Language :: Python :: 3.10
Classifier: Programming Language :: Python :: 3.11
Classifier: Programming Language :: Python :: 3.12
Classifier: Programming Language :: Python :: 3.13
Classifier: Topic :: Database
Classifier: Topic :: Scientific/Engineering
Classifier: Topic :: Software Development :: Libraries :: Python Modules
Classifier: Environment :: Console
Classifier: Intended Audience :: Science/Research
Requires-Python: >=3.9
License-File: LICENSE
Requires-Dist: click>=8.0.0
Requires-Dist: rich>=13.0.0
Requires-Dist: tabulate>=0.9.0
Requires-Dist: pandas>=1.5.0
Requires-Dist: pyarrow>=10.0.0
Requires-Dist: duckdb>=0.9.0
Requires-Dist: boto3>=1.26.0
Requires-Dist: google-cloud-storage>=2.5.0
Requires-Dist: azure-storage-blob>=12.14.0
Requires-Dist: hdfs>=2.6.0
Requires-Dist: requests>=2.25.0
Provides-Extra: dev
Requires-Dist: pytest>=7.0.0; extra == "dev"
Requires-Dist: pytest-cov>=4.0.0; extra == "dev"
Requires-Dist: black>=22.0.0; extra == "dev"
Requires-Dist: flake8>=5.0.0; extra == "dev"
Requires-Dist: mypy>=0.991; extra == "dev"
Provides-Extra: docs
Requires-Dist: sphinx>=5.0.0; extra == "docs"
Requires-Dist: sphinx-rtd-theme>=1.2.0; extra == "docs"
Dynamic: license-file
